PlayCoinGame
