Metadata-Version: 2.1
Name: PlayCoinGame
Version: 1.0.2
Summary: A package that plays guess the coin
Author: Guido Xhindoli
Author-email: <mail@gmail.com>
Keywords: pythonsdaal,PlayCoinGame,coin-game,sda,SDA
Classifier: Development Status :: 1 - Planning
Classifier: Intended Audience :: Developers
Classifier: Programming Language :: Python :: 3
Classifier: Operating System :: Unix
Classifier: Operating System :: MacOS :: MacOS X
Classifier: Operating System :: Microsoft :: Windows
